catena4j/__init__.py
catena4j/_bootstrap.py
catena4j/bootstrap.py
catena4j/c4jutil.py
catena4j/config.py
catena4j/d4jutil.py
catena4j/dispatcher.py
catena4j/env.py
catena4j/exceptions.py
catena4j/user_setup.py
catena4j/util.py
catena4j/cli/__init__.py
catena4j/cli/manager.py
catena4j/cli/parser.py
catena4j/commands/__init__.py
catena4j/commands/checkout.py
catena4j/commands/compile.py
catena4j/commands/export.py
catena4j/commands/test.py
catena4j/commands/xids.py
catena4j/loaders/Chart.py
catena4j/loaders/Cli.py
catena4j/loaders/Closure.py
catena4j/loaders/Codec.py
catena4j/loaders/Collections.py
catena4j/loaders/Compress.py
catena4j/loaders/Csv.py
catena4j/loaders/Gson.py
catena4j/loaders/JacksonCore.py
catena4j/loaders/JacksonDatabind.py
catena4j/loaders/JacksonXml.py
catena4j/loaders/Jsoup.py
catena4j/loaders/JxPath.py
catena4j/loaders/Lang.py
catena4j/loaders/Math.py
catena4j/loaders/Mockito.py
catena4j/loaders/Time.py
catena4j/loaders/__init__.py
catena4j/loaders/loader.py
catena4j/loaders/post_checkout_util.py
catena4j/loaders/project_loader.py
catena4j/projects/Chart/Chart.compile.xml
catena4j/projects/Chart/Chart.export.xml
catena4j/projects/Chart/bugs-registry.csv
catena4j/projects/Chart/14/1.classes.modified
catena4j/projects/Chart/14/1.src.patch
catena4j/projects/Chart/14/1.test.patch
catena4j/projects/Chart/14/1.tests.trigger
catena4j/projects/Chart/14/2.classes.modified
catena4j/projects/Chart/14/2.src.patch
catena4j/projects/Chart/14/2.test.patch
catena4j/projects/Chart/14/2.tests.trigger
catena4j/projects/Chart/14/3.classes.modified
catena4j/projects/Chart/14/3.src.patch
catena4j/projects/Chart/14/3.test.patch
catena4j/projects/Chart/14/3.tests.trigger
catena4j/projects/Chart/14/4.classes.modified
catena4j/projects/Chart/14/4.src.patch
catena4j/projects/Chart/14/4.test.patch
catena4j/projects/Chart/14/4.tests.trigger
catena4j/projects/Chart/15/1.classes.modified
catena4j/projects/Chart/15/1.src.patch
catena4j/projects/Chart/15/1.test.patch
catena4j-2.0.1.dist-info/LICENSE
catena4j-2.0.1.dist-info/METADATA
catena4j-2.0.1.dist-info/WHEEL
catena4j-2.0.1.dist-info/entry_points.txt
catena4j-2.0.1.dist-info/top_level.txt
catena4j-2.0.1.dist-info/RECORD
