Metadata-Version: 2.1
Name: catena4j
Version: 2.0.1
Summary: A dataset and tool for evaluating techniques on repairing indivisible multi-hunk bugs
Author-email: universetraveller <93870078+universetraveller@users.noreply.github.com>
Maintainer-email: universetraveller <93870078+universetraveller@users.noreply.github.com>
License: MIT License
Project-URL: Homepage, https://github.com/universetraveller/catena4j
Project-URL: Documentation, https://github.com/universetraveller/catena4j#readme
Project-URL: Repository, https://github.com/universetraveller/catena4j
Project-URL: Issues, https://github.com/universetraveller/catena4j/issues
Keywords: defects4j,bug-dataset,program-repair,fault-localization,software-testing,multi-hunk-bugs,indivisible-bugs
Classifier: Development Status :: 4 - Beta
Classifier: Intended Audience :: Developers
Classifier: Intended Audience :: Science/Research
Classifier: Operating System :: OS Independent
Classifier: Programming Language :: Python :: 3
Classifier: Programming Language :: Python :: 3.8
Classifier: Programming Language :: Python :: 3.9
Classifier: Programming Language :: Python :: 3.10
Classifier: Programming Language :: Python :: 3.11
Classifier: Programming Language :: Python :: 3.12
Classifier: Programming Language :: Java
Classifier: Topic :: Software Development :: Testing
Classifier: Topic :: Software Development :: Quality Assurance
Classifier: Topic :: Scientific/Engineering
Requires-Python: >=3.8
License-File: LICENSE
Provides-Extra: dev
Requires-Dist: build>=1.0.0; extra == "dev"
Requires-Dist: twine>=4.0.0; extra == "dev"
